langcraft/__init__.py
langcraft/action.py
langcraft/logging.py
langcraft/utils.py
langcraft/llm/__init__.py
langcraft/llm/claude.py
langcraft/llm/gemini.py
langcraft/llm/gpt.py
langcraft/llm/llm_action.py
langcraft/llm/llm_completion.py
langcraft/llm/llm_embedding.py
langcraft/llm/llm_models.py
langcraft/web/__init__.py
langcraft/web/jina.py
unimpossible_langcraft-0.1.2.dist-info/LICENSE
unimpossible_langcraft-0.1.2.dist-info/METADATA
unimpossible_langcraft-0.1.2.dist-info/WHEEL
unimpossible_langcraft-0.1.2.dist-info/top_level.txt
unimpossible_langcraft-0.1.2.dist-info/RECORD
